pylogging/__init__.py
pylogging/main.py
pyloggging-0.0.6.dist-info/LICENSE
pyloggging-0.0.6.dist-info/METADATA
pyloggging-0.0.6.dist-info/WHEEL
pyloggging-0.0.6.dist-info/top_level.txt
pyloggging-0.0.6.dist-info/RECORD
