Metadata-Version: 2.1
Name: pyloggging
Version: 0.0.6
Summary: Logging package
Home-page: https://github.com/YoungDev06/py-logging
Author: TheDev
Author-email: author@example.com
Project-URL: Bug Tracker, https://github.com/YoungDev06/py-logging/issues
Classifier: Programming Language :: Python :: 3
Classifier: License :: OSI Approved :: MIT License
Classifier: Operating System :: OS Independent
Requires-Python: >=3.6
License-File: LICENSE
